LICENSE.txt
MANIFEST.in
README.markdown
setup.py
cereal/__init__.py
cereal/cereal.py
cereal/functions.py
cereal/serializers.py
cereal/urls.py
cereal/views.py
cereal/templates/cereal/docs.html
cereal_box.egg-info/PKG-INFO
cereal_box.egg-info/SOURCES.txt
cereal_box.egg-info/dependency_links.txt
cereal_box.egg-info/top_level.txt