Metadata-Version: 1.0
Name: cereal-box
Version: 1.0.4
Summary: Data feed library for Django models.
Home-page: http://www.github.com/ff0000/cereal-box/
Author: RED Interactive Agency
Author-email: geeks@ff0000.com
License: MIT license
Download-URL: http://www.github.com/ff0000/cereal-box/
Platform: UNKNOWN
Classifier: Development Status :: 3 - Alpha
Classifier: Environment :: Web Environment
Classifier: Framework :: Django
Classifier: Intended Audience :: Developers
Classifier: License :: OSI Approved :: MIT License
Classifier: Natural Language :: English
Classifier: Programming Language :: Python
Classifier: Topic :: Internet :: WWW/HTTP :: Dynamic Content
